{
  "description": {
    "title": "",
    "text": ""
  },
  "links_1": {
    "list_pages": false,
    "title": "Páginas",
    "list": [
      {
        "text": "BLOG",
        "url": "blog.duasxicaras.com.br"
      },
      {
        "url": "https://www.duasxicaras.com.br/pages/contato",
        "text": "CONTATO"
      },
      {
        "text": "CONDIÇÕES DE ENTREGA",
        "url": "https://www.duasxicaras.com.br/pages/entrega"
      },
      {
        "url": "https://www.duasxicaras.com.br/pages/faq",
        "text": "DÚVIDAS FREQUENTES"
      },
      {
        "text": "GARANTIA",
        "url": "https://www.duasxicaras.com.br/pages/garantia"
      },
      {
        "text": "MARCAS",
        "url": "https://www.duasxicaras.com.br/pages/marcas"
      },
      {
        "text": "FORMAS DE PAGAMENTO",
        "url": "https://www.duasxicaras.com.br/pages/pagamentos"
      },
      {
        "text": "POLÍTICAS DE PRIVACIDADE",
        "url": "https://www.duasxicaras.com.br/pages/privacidade"
      },
      {
        "text": "SOBRE NÓS",
        "url": "https://www.duasxicaras.com.br/pages/sobre-nos"
      },
      {
        "url": "https://www.duasxicaras.com.br/pages/termos",
        "text": "TERMOS DE SERVIÇO"
      },
      {
        "text": "TROCAS E DEVOLUÇÕES",
        "url": "https://www.duasxicaras.com.br/pages/trocas"
      }
    ]
  },
  "links_2": {
    "list_categories": true,
    "title": "Categorias",
    "list": []
  },
  "contacts": {
    "title": "Contatos",
    "texto": "NOSSO HORÁRIO DE ATENDIMENTO É DE SEG.: À SEX.: DAS 9H ÀS 17H30.",
    "phone_wpp": true,
    "socials": true,
    "email": true,
    "address": true
  },
  "stamps_title": "Certificados",
  "stamps": [
    {
      "src": "/img/uploads/ssl-safe.png",
      "alt": "Secure connection"
    }
  ],
  "payment_methods": {
    "bb": true,
    "visa": true,
    "boleto": true,
    "aura": false,
    "banrisul": false,
    "elo": true,
    "hipercard": false,
    "hsbc": false,
    "bradesco": true,
    "santander": false,
    "mastercard": true,
    "citibank": false,
    "title": "Formas de Pagamento",
    "mais": false,
    "pix": true,
    "itau": true
  },
  "credits": ""
}